netsuite/Netsuite.py
netsuite/NetsuiteToken.py
netsuite/__init__.py
netsuite/exceptions.py
netsuite/module_loading.py
netsuite/settings.py
netsuite/api_clients/__init__.py
netsuite/api_clients/api_client.py
netsuite/api_clients/configuration.py
netsuite/api_clients/rest.py
netsuite/api_clients/api/__init__.py
netsuite/api_clients/api/query_api.py
netsuite/api_clients/api/restlet_api.py
netsuite/netsuite_rest_client/__init__.py
netsuite/netsuite_rest_client/rest_api_client.py
netsuite/scripts/__init__.py
netsuite/scripts/cli.py
netsuite/storages/BaseStorage.py
netsuite/storages/InMemoryStorage.py
netsuite/storages/JSONStorage.py
netsuite/storages/__init__.py
netsuite/swagger_client/__init__.py
netsuite/swagger_client/api_client.py
netsuite/swagger_client/configuration.py
netsuite/swagger_client/rest.py
netsuite/swagger_client/rest_client.py
netsuite/swagger_client/api/__init__.py
netsuite/swagger_client/api/contact_api.py
netsuite/swagger_client/api/customer_api.py
netsuite/swagger_client/api/message_api.py
netsuite/swagger_client/api/query_api.py
netsuite/swagger_client/api/restlet_api.py
netsuite/swagger_client/models/__init__.py
netsuite/swagger_client/models/contact.py
netsuite/swagger_client/models/contact_collection.py
netsuite/swagger_client/models/contact_custom_form.py
netsuite/swagger_client/models/customer.py
netsuite/swagger_client/models/customer_address_book_address_book_address.py
netsuite/swagger_client/models/customer_address_book_collection.py
netsuite/swagger_client/models/customer_address_book_element.py
netsuite/swagger_client/models/customer_alcohol_recipient_type.py
netsuite/swagger_client/models/customer_campaigns_collection.py
netsuite/swagger_client/models/customer_campaigns_element.py
netsuite/swagger_client/models/customer_collection.py
netsuite/swagger_client/models/customer_contact_roles_collection.py
netsuite/swagger_client/models/customer_contact_roles_element.py
netsuite/swagger_client/models/customer_custom_form.py
netsuite_python-2.1.5.dist-info/LICENSE
netsuite_python-2.1.5.dist-info/METADATA
netsuite_python-2.1.5.dist-info/WHEEL
netsuite_python-2.1.5.dist-info/entry_points.txt
netsuite_python-2.1.5.dist-info/top_level.txt
netsuite_python-2.1.5.dist-info/RECORD
