Metadata-Version: 2.2
Name: netsuite_python
Version: 2.1.5
Summary: Python SDK for Netsuite API with Flask Integration
Home-page: https://github.com/codinlikewilly/netsuite_python
Author: Will @ TheAPIGuys
Author-email: will@theapiguys.com
License-File: LICENSE
Requires-Dist: Click
Requires-Dist: requests
Requires-Dist: PyJWT
Requires-Dist: urllib3>=1.15
Requires-Dist: six>=1.10
Requires-Dist: certifi
Requires-Dist: python-dateutil
Requires-Dist: pyOpenSSL
Requires-Dist: cryptography
Dynamic: author
Dynamic: author-email
Dynamic: description
Dynamic: description-content-type
Dynamic: home-page
Dynamic: requires-dist
Dynamic: summary
